setup.py
cratis/__init__.py
cratis/add.py
cratis/bootstrap.py
cratis/cli.py
cratis/django.py
cratis/env.py
cratis/features.py
cratis/settings.py
cratis/urls.py
cratis/utils.py
cratis/wsgi.py
cratis/generators/__init__.py
cratis/generators/codegen.py
cratis/generators/module.py
cratis/generators/requirements.py
django_cratis.egg-info/PKG-INFO
django_cratis.egg-info/SOURCES.txt
django_cratis.egg-info/dependency_links.txt
django_cratis.egg-info/entry_points.txt
django_cratis.egg-info/requires.txt
django_cratis.egg-info/top_level.txt
tests/__init__.py
tests/_markers.py
tests/test_add.py
tests/test_django.py
tests/test_init.py
tests/test_utils.py