Metadata-Version: 1.0
Name: django-cratis
Version: 0.9.1
Summary: Django-cratis is a way to group together django applications, so they form reusable features.
Home-page: UNKNOWN
Author: Alex Rudakov
Author-email: ribozz@gmail.com
License: Simplified BSD License
Platform: UNKNOWN
